joypy/__init__.py
joypy/joyplot.py
joypy-0.2.6.dist-info/LICENSE
joypy-0.2.6.dist-info/METADATA
joypy-0.2.6.dist-info/WHEEL
joypy-0.2.6.dist-info/top_level.txt
joypy-0.2.6.dist-info/RECORD
